LICENSE
MANIFEST.in
README.md
setup.py
yaacl/__init__.py
yaacl/admin.py
yaacl/decorators.py
yaacl/functions.py
yaacl/managers.py
yaacl/models.py
yaacl/signals.py
yaacl/views.py
yaacl.egg-info/PKG-INFO
yaacl.egg-info/SOURCES.txt
yaacl.egg-info/dependency_links.txt
yaacl.egg-info/not-zip-safe
yaacl.egg-info/requires.txt
yaacl.egg-info/top_level.txt
yaacl/management/__init__.py
yaacl/management/commands/__init__.py
yaacl/management/commands/show_acl.py
yaacl/management/commands/sync_acl.py
yaacl/migrations/0001_initial.py
yaacl/migrations/0002_m2m_relations.py
yaacl/migrations/__init__.py
yaacl/templates/yaacl/no_access.html
yaacl/templatetags/__init__.py
yaacl/templatetags/acl.py