Metadata-Version: 1.1
Name: yaacl
Version: 0.8.1
Summary: Yet another access control list (ACL) per view for Django
Home-page: https://github.com/Alkemic/yaACL
Author: Daniel Czuba
Author-email: dc@danielczuba.pl
License: MIT
Keywords: django,acl,admin
Platform: UNKNOWN
Classifier: Development Status :: 4 - Beta
Classifier: Environment :: Web Environment
Classifier: Framework :: Django
Classifier: Intended Audience :: Developers
Classifier: License :: OSI Approved :: MIT License
Classifier: Operating System :: OS Independent
Classifier: Programming Language :: Python
